<?xml version="1.0" encoding="UTF-8" standalone="yes"?>
<imgdir name="3006275.img">
<imgdir name="info">
<int name="hideName" value="1"/>
<int name="forceMove" value="1"/>
<imgdir name="illustration2">
<canvas name="base" width="1" height="1">
</canvas>
<imgdir name="face">
<canvas name="0" width="396" height="306">
<vector name="origin" x="68" y="184"/>
<int name="z" value="0"/>
<string name="_hash" value="0cb8de2230b73e29e0af3a784a677cf4f61957c14406e9d9ecd96011afdf34ca"/>
</canvas>
</imgdir>
</imgdir>
</imgdir>
<imgdir name="stand">
<canvas name="0" width="84" height="93">
<vector name="origin" x="49" y="93"/>
<int name="z" value="0"/>
<string name="_hash" value="5143fecb8df52ec13963a3226a6ee1d2b2d14dbe3d6af59e449282b07821f99d"/>
</canvas>
</imgdir>
<imgdir name="move">
<canvas name="0" width="84" height="93">
<vector name="origin" x="49" y="93"/>
<int name="z" value="0"/>
<int name="delay" value="150"/>
<string name="_hash" value="cd03c5c279384951507fb8ecd00f21df94dab0bda16e1a6fbc1597524fdf61ec"/>
</canvas>
<canvas name="1" width="84" height="92">
<vector name="origin" x="49" y="92"/>
<int name="z" value="0"/>
<int name="delay" value="150"/>
<string name="_hash" value="427c50081d5f57056b8d4951d8f267ab3ca527f0e67a866fd1c02ab798b4fbcf"/>
</canvas>
<canvas name="2" width="84" height="93">
<vector name="origin" x="49" y="93"/>
<int name="z" value="0"/>
<int name="delay" value="150"/>
<string name="_hash" value="0801f713001ad865b78eea3f257ead352049d891f026c91843c00e54176fdb6e"/>
</canvas>
<canvas name="3" width="84" height="92">
<vector name="origin" x="49" y="92"/>
<int name="z" value="0"/>
<int name="delay" value="150"/>
<string name="_hash" value="f271ec7bcb591a53ca2e199b483578a139b7f74c0bc77004dcd8eb90ccebd2ab"/>
</canvas>
</imgdir>
<imgdir name="doctor">
<canvas name="0" width="84" height="93">
<vector name="origin" x="49" y="93"/>
<int name="z" value="0"/>
<int name="delay" value="180"/>
<string name="_hash" value="344a16795f9a87b69711ff568da063715636bec235ac1ed96d1f1783ffa14b9d"/>
</canvas>
<canvas name="1" width="84" height="93">
<vector name="origin" x="49" y="93"/>
<int name="z" value="0"/>
<int name="delay" value="180"/>
<string name="_hash" value="25820172bdc8e42ab738c1c26a53e81b253c07309a474118185f7e6ed2752b0f"/>
</canvas>
<canvas name="2" width="84" height="93">
<vector name="origin" x="49" y="93"/>
<int name="z" value="0"/>
<int name="delay" value="180"/>
<string name="_hash" value="915630d4267987ca265ae219fc9c60d8ab9b5b5799f0dde4ed7bce3ad2844067"/>
</canvas>
<canvas name="3" width="84" height="93">
<vector name="origin" x="49" y="93"/>
<int name="z" value="0"/>
<int name="delay" value="180"/>
<string name="_hash" value="40ea792939183ea00ec5a64f9628b02a8f7d7f6d59a87c295f4f9863aefe7ff6"/>
</canvas>
<canvas name="4" width="84" height="93">
<vector name="origin" x="49" y="93"/>
<int name="z" value="0"/>
<int name="delay" value="180"/>
<string name="_hash" value="482cdd4e0657556b454449f328c8aab67c8f29886c83d510861178329413bb35"/>
</canvas>
<canvas name="5" width="84" height="93">
<vector name="origin" x="49" y="93"/>
<int name="z" value="0"/>
<int name="delay" value="180"/>
<string name="_hash" value="44d4288d9dc58853f4691cfb0fa16d4fb1df93a99fad5802e031d7ea26ad5f9e"/>
</canvas>
<canvas name="6" width="84" height="93">
<vector name="origin" x="49" y="93"/>
<int name="z" value="0"/>
<int name="delay" value="180"/>
<string name="_hash" value="2ab76fb0ae099aa39d1784026e126711db843ac714bfc30d9583891105e52cb1"/>
</canvas>
<canvas name="7" width="84" height="93">
<vector name="origin" x="49" y="93"/>
<int name="z" value="0"/>
<int name="delay" value="180"/>
<string name="_hash" value="1dec8d5e9e6350b29dde8bae0db5269f2b4b205bdb966d392eec5697a91a86a2"/>
</canvas>
<int name="special" value="1"/>
</imgdir>
<imgdir name="doctor2">
<canvas name="0" width="84" height="93">
<vector name="origin" x="49" y="93"/>
<int name="z" value="0"/>
<int name="delay" value="180"/>
</canvas>
<int name="special" value="1"/>
</imgdir>
</imgdir>
