<?xml version="1.0" encoding="UTF-8" standalone="yes"?><imgdir name="11371.img"><imgdir name="QuestInfo"><string name="name" value="원숭이 인형을 되찾아주세요!"/><int name="area" value="50"/><int name="autoStart" value="1"/><int name="autoComplete" value="1"/><string name="0" value="가가가 도둑맞은 원숭이 인형을 되찾아 달라고 한다. 화면 왼쪽의 이벤트 알리미를 클릭하거나 가가에게 찾아가 보자."/><string name="1" value="가가의 #t03994360#은 아래로 차이가 10레벨 이하, 위로 차이가 20레벨 이하인 몬스터들에게서 얻을 수 있다.
#t03994360#을 30개 모아서 가가에게 가져가면 계정 내 이동이 가능하고 먹으면 경험치를 얻을 수 있는 #t02430395#를 얻을 수 있다.
추가로, 계정 내 이동 가능하고 캐논 슈터가 마시면 경험치를 얻을 수 있는 #t02430396#도 얻을 수 있다."/><string name="2" value="가가의 원숭이 인형을 되찾아 주고 #i02430395##b#t02430395##k와 #i02430396##b#t02430396##k을 받았다. 10분 뒤에 다시 수행하고 보상을 받을 수 있다."/><string name="demandSummary" value="#i3994360:# #t3994360:# #c3994360# / 30
"/><string name="rewardSummary" value="#Wbasic#
#i2430395:# #t2430395:# 1 개
#i2430396:# #t2430396:# 1 개"/></imgdir><imgdir name="Check"><imgdir name="0"><int name="npc" value="9000021"/><int name="lvmin" value="13"/><string name="start" value="201106300000"/><string name="end" value="201107180000"/><string name="start_t" value="201106160000"/><string name="end_t" value="201107180000"/><int name="interval" value="10"/><int name="normalAutoStart" value="1"/><string name="startscript" value="q11371s"/><imgdir name="quest"><imgdir name="0"><int name="id" value="11370"/><int name="state" value="2"/></imgdir></imgdir></imgdir><imgdir name="1"><int name="npc" value="9000021"/><string name="endscript" value="q11371e"/><imgdir name="item"><imgdir name="0"><int name="id" value="3994360"/><int name="count" value="30"/></imgdir></imgdir></imgdir></imgdir><imgdir name="Act"><imgdir name="0"></imgdir><imgdir name="1"><imgdir name="item"><imgdir name="0"><int name="id" value="2430395"/><int name="count" value="1"/><string name="potentialGrade" value="노멀"/></imgdir><imgdir name="1"><int name="id" value="3994360"/><int name="count" value="-30"/><string name="potentialGrade" value="노멀"/></imgdir><imgdir name="2"><int name="id" value="2430396"/><int name="count" value="1"/><string name="potentialGrade" value="노멀"/></imgdir></imgdir></imgdir></imgdir><imgdir name="Say"><imgdir name="0"><string name="0" value="원숭이 인형을 되찾아 주기 위해 오셨군요. 그럼 지금 바로 시작해 주시겠어요?"/><imgdir name="stop"></imgdir><imgdir name="yes"><string name="0" value="#t03994360#은 #b#h0##k 님의 레벨보다 #r10레벨 이하로 낮거나, 20레벨 이하로 높은 몬스터들#k에게서 획득하실 수 있어요. 그럼, 원숭이 인형을 꼭 되찾아 와 주세요! 저는 보상으로 드릴 #b#t02430395##k와 #b#t02430396##k을 준비하고 기다릴게요."/></imgdir><imgdir name="no"><string name="0" value="#b#h0##k 님의 도움이 꼭 필요해요. 꼭 다시 오셔서 저를 도와주세요."/></imgdir></imgdir><imgdir name="1"></imgdir></imgdir></imgdir>