<?xml version="1.0" encoding="UTF-8" standalone="yes"?><imgdir name="11855.img"><imgdir name="QuestInfo"><string name="name" value="카산드라의 예지몽"/><int name="area" value="50"/><string name="0" value="신기한 꿈을 꿨다는 카산드라의 이야기를 들어보자."/><string name="1" value="카산드라는 #b황금돼지#k가 나오는 꿈을 꿨다면서 왠지 좋은 일이 생길 것 같다고 했다. 꿈의 내용을 물어보니 메이플월드였다고 하는데...\n왠지 그 장소에 다시 가면 #b황금돼지#k가 있을 것 같다면서 황금돼지를 잡으면 좋은 일이 생긴다는 전설이 있으니 한번 잡아 보라고 했다."/><string name="2" value="카산드라는 #b황금돼지#k가 나오는 꿈을 꿨다면서 왠지 좋은 일이 생길 것 같다고 했다. 꿈의 내용을 물어보니 메이플월드였다고 하는데...\n왠지 그 장소에 다시 가면 #b황금돼지#k가 있을 것 같다면서 황금돼지를 잡으면 좋은 일이 생긴다는 전설이 있다고 알려줬다."/><int name="autoStart" value="1"/><int name="autoComplete" value="1"/><string name="demandSummary" value="#o9101026# #a118551#
"/><string name="rewardSummary" value="#Wselect#
#i2046320:# #t2046320:# 1 개
#i2046321:# #t2046321:# 1 개
#i2046322:# #t2046322:# 1 개
#i2046323:# #t2046323:# 1 개
"/></imgdir><imgdir name="Check"><imgdir name="0"><int name="npc" value="9010010"/><int name="lvmin" value="13"/><string name="end_t" value="201110130000"/><int name="normalAutoStart" value="1"/><string name="end" value="201110250000"/></imgdir><imgdir name="1"><int name="npc" value="9010010"/><imgdir name="mob"><imgdir name="0"><int name="id" value="9101026"/><int name="count" value="1"/></imgdir></imgdir></imgdir></imgdir><imgdir name="Act"><imgdir name="0"></imgdir><imgdir name="1"><imgdir name="item"><imgdir name="0"><int name="id" value="2046320"/><int name="count" value="1"/><int name="prop" value="-1"/><string name="potentialGrade" value="노멀"/></imgdir><imgdir name="1"><int name="id" value="2046321"/><int name="count" value="1"/><int name="prop" value="-1"/><string name="potentialGrade" value="노멀"/></imgdir><imgdir name="2"><int name="id" value="2046322"/><int name="count" value="1"/><int name="prop" value="-1"/><string name="potentialGrade" value="노멀"/></imgdir><imgdir name="3"><int name="id" value="2046323"/><int name="count" value="1"/><int name="prop" value="-1"/><string name="potentialGrade" value="노멀"/></imgdir></imgdir></imgdir></imgdir><imgdir name="Say"><imgdir name="0"><string name="0" value="#b#h0##k! 내가 어제 밤에 기막힌 꿈을 꿨어! 무려 꿈에 #b황금돼지#k가 나왔다고!! 복권이라도 사야하는 거 아닐까?\n황금돼지를 잡으려고 막~ 쫓아다녔어. 분명 메이플월드 어딘가였는데 통 기억이 안 나네? 결국 마지막에 #b황금돼지#k를 잡긴 잡았는데 바로 꿈에서 깨버렸지 뭐야."/><string name="1" value="그런데 어쩐지 꿈이 아니라 생시인 것만 같아. 지금 이 순간 메이플월드 어딘가에서 #b황금돼지#k가 뛰어다니고 있을 것만 같아. 네가 한번 찾아보지 않겠어?"/><imgdir name="stop"></imgdir><imgdir name="yes"><string name="0" value="전설에 따르면 황금돼지를 잡으면 좋은 일이 생긴데, 그말이 진짜인지 네가 황금돼지를 잡아보고 나에게 알려줘. 알았지?\n아무 황금돼지나 잡으면 안되고 니 레벨과 비슷한 황금돼지를 잡아야해. 알았지? 너보다 11레벨 이상 낮거나 21레벨 이상 높은 황금돼지는 쳐주지 않을거야."/></imgdir><imgdir name="no"><string name="0" value="전설에 따르면 황금돼지를 잡으면 좋은 일이 생긴데, 그말이 진짜일까?"/></imgdir></imgdir><imgdir name="1"><int name="ask" value="1"/><string name="0" value="진짜 #b황금 꿈돼지#k를 발견했구나? 어때? 좋은 일은 생겼어?\r\n#L0##b글쎄...앞으로 좋은 일이 생기려나?#l\n#k"/><string name="1" value="그래 앞으로 좋은 일이 생길지도 몰라. 좋은 정보를 얻었어. 좋아 그럼 나도 선물을 하나 줄테니까 원하는 것을 골라봐."/><imgdir name="yes"><string name="0" value="나도 황금 꿈돼지를 잡아보고 싶다. 하지만 할 일이 많아서 자리를 오랫동안 비울 수도 없고...꿈나라에서나 잡아봐야 하나?"/></imgdir><imgdir name="stop"><imgdir name="0"><int name="answer" value="1"/></imgdir><imgdir name="mob"><string name="0" value="전설에 따르면 황금돼지를 잡으면 좋은 일이 생긴데, 그말이 진짜인지 네가 황금돼지를 잡아보고 나에게 알려줘. 알았지?\n아무 황금돼지나 잡으면 안되고 니 레벨과 비슷한 황금돼지를 잡아야해. 알았지? 너보다 11레벨 이상 낮거나 21레벨 이상 높은 황금돼지는 쳐주지 않을거야."/></imgdir></imgdir></imgdir></imgdir></imgdir>