<?xml version="1.0" encoding="UTF-8" standalone="yes"?><imgdir name="12221.img"><imgdir name="QuestInfo"><string name="name" value="[화이트데이] 더욱 강해져서 돌아온 커플 몬스터!"/><int name="area" value="50"/><int name="autoStart" value="1"/><int name="autoPreComplete" value="1"/><string name="0" value="봄바람과 함께 그들이 돌아왔다! 커플 몬스터!
온 사방에 닭살을 뿌리고 다니는 그들을 격퇴하면 놀라운 보상을 얻을 수 있다는데?
#p9010010#에게서 설명을 듣자."/><string name="1" value="봄바람과 함께 그들이 돌아왔다! 커플 몬스터!
온 사방에 닭살을 뿌리고 다니는 그들을 격퇴하면 놀라운 보상을 얻을 수 있다는데?"/><string name="2" value="봄바람과 함께 그들이 돌아왔다! 커플 몬스터!
온 사방에 닭살을 뿌리고 다니는 그들을 격퇴하면 놀라운 보상을 얻을 수 있다는데?

이하는 커플 몬스터가 출몰한다는 곳과 해당 장소에서 출몰하는 커플 몬스터의 레벨이다. 사냥터 선정에 참고하도록 하자.\n\n\n#b[헤네시스] 골렘의 사원 일대(20Lv)\n[커닝스퀘어] 1층 2층 일대(40Lv)\n[오르비스] 세가지 빛의 정원2 일대(40Lv)\n[아랫마을] 필드 일대(60Lv)\n[지구방위본부] 로스웰초원 일대(60Lv)\n[아리안트] 선셋로드 일대(80Lv)\n[마가티아] 알카드노 연구소 일대(80Lv)\n[빨간코해적단] 해적단 소굴 일대(100Lv)#k\##b[리프레 전장] 켄타우로스 지역 일대(120Lv)\n[황금사원]수행자의 숲 일대(120Lv)\n[리프레 용의숲] 용의숲 일대(140Lv)\n[신전] 추억의 길 일대(160Lv)\n[신전] 후회의 길 일대(160Lv)\n[신전] 망각의 길 일대(160Lv)#k

"/></imgdir><imgdir name="Check"><imgdir name="0"><int name="npc" value="9010010"/><int name="lvmin" value="10"/><string name="start" value="201203080000"/><string name="end" value="201203220000"/><string name="start_t" value="201202130000"/><string name="end_t" value="201203220000"/><int name="normalAutoStart" value="1"/></imgdir><imgdir name="1"></imgdir></imgdir><imgdir name="Act"><imgdir name="0"></imgdir><imgdir name="1"></imgdir></imgdir><imgdir name="Say"><imgdir name="0"><string name="0" value="왔구나. #b#h0##k. 기다리고 있었어.\n실은 부탁할 일이 있거든."/><string name="1" value="#r그들#k이 돌아왔어."/><string name="2" value="…그들이 누구냐고?\n누구긴 누구야. #r커플 몬스터#k들이지!\r\n"/><string name="3" value="이대로 그들이 메이플 월드에 염장을 지르고 다닌다면 나같은 솔로들은 봄이 채 오기도 전에 옆구리가 시려서 얼어버릴지도 몰라. 부탁이니 수많은 솔로들을 대신해서 #r커플 몬스터#k를 격퇴해줘!"/><imgdir name="stop"></imgdir><imgdir name="no"><string name="0" value="뭐, 뭐라고?\n혹시 넌 커플제국의 스파이였던 거야?!"/></imgdir></imgdir><imgdir name="1"><imgdir name="yes"><string name="0" value="커플 몬스터는 메이플 월드의 각지에서 등장해 뭇 사람들의 염장을 지르고 있어. 어떤 사냥터에서 어느 레벨의 커플 몬스터가 등장하는 지는 퀘스트 정보에서 안내하고 있으니 사냥을 나서기 전에 반드시 확인하면 좋아."/><string name="1" value="참, 자신보다 #b레벨이 11이상 낮거나, 21이상 높은#k 커플 몬스터는 잡아도 보상은 받을 수 없으니까, 꼭 #b자신과 레벨이 비슷한 커플 몬스터#k를 잡을 것. 알았지?"/></imgdir><imgdir name="stop"><imgdir name="default"><string name="0" value="으잉? #r커플 몬스터#k를 잡으라니까 뭐하고 있는 거야?\n너, 혹시……?"/></imgdir></imgdir></imgdir></imgdir></imgdir>