<?xml version="1.0" encoding="UTF-8" standalone="yes"?><imgdir name="12405.img"><imgdir name="QuestInfo"><string name="name" value="[유물대회] 고대 유물발굴 대회 다섯 번째 날"/><int name="area" value="50"/><int name="autoStart" value="1"/><string name="0" value="유물발굴 대회에 5일 참가했다. 이벤트 알리미를 통해 참가 선물과 이벤트 스탬프를 받아가자."/><string name="1" value="유물발굴 대회에 5일 참가했다. 이벤트 알리미를 통해 참가 선물과 이벤트 스탬프를 받아가자."/><string name="2" value="유물발굴 대회에 5일 참가했다. 이벤트 알리미를 통해 참가 선물과 이벤트 스탬프를 받았다. \r\n#i01012316# #t01012316#"/></imgdir><imgdir name="Check"><imgdir name="0"><int name="normalAutoStart" value="1"/><int name="npc" value="9010044"/><int name="infoNumber" value="12409"/><string name="startscript" value="q12405s"/><imgdir name="infoex"><imgdir name="0"><string name="value" value="5"/><int name="cond" value="1"/></imgdir></imgdir><imgdir name="quest"><imgdir name="0"><int name="id" value="12404"/><int name="state" value="2"/></imgdir></imgdir><string name="end" value="201205030000"/><string name="end_t" value="201204190000"/></imgdir><imgdir name="1"></imgdir></imgdir><imgdir name="Act"><imgdir name="0"><imgdir name="item"><imgdir name="0"><int name="id" value="1012316"/><int name="count" value="1"/><string name="potentialGrade" value="노멀"/><int name="period" value="43200"/></imgdir></imgdir></imgdir><imgdir name="1"></imgdir></imgdir><imgdir name="Say"><imgdir name="0"><string name="0" value="유물 발굴대회에 5일 참가한 것을 축하한다. 준비해 놓은 선물을 받아보겠어?"/><imgdir name="stop"></imgdir></imgdir><imgdir name="1"><imgdir name="yes"><string name="0" value="6일차 선물도 준비해 놓을테니 다음엔 조금 더 열심히 발굴해서 기막히게 멋진 유물을 발굴해 보라구~"/></imgdir></imgdir></imgdir></imgdir>