<?xml version="1.0" encoding="UTF-8" standalone="yes"?><imgdir name="1732.img"><imgdir name="QuestInfo"><string name="name" value="온도 유지는 필수!"/><int name="area" value="4"/><string name="0" value="슈피겔만이 뭔가 부탁할 것이 있는 눈치이다."/><string name="1" value="부화실의 온도유지를 위해 알을 따뜻하게 해 줄 따뜻한 깃털이 필요하다. 하프를 처치하고 따뜻한 깃털을 모아야 한다."/><string name="2" value="따뜻한 깃털을 다 모아왔다. 이 정도면 온도를 유지하는데 문제 없겠지?"/><string name="demandSummary" value="#i4033204:# #t4033204:# #c4033204# / 10
"/><imgdir name="validField"><int name="0" value="956030000"/><int name="1" value="956030001"/><int name="2" value="956030002"/><int name="3" value="956030003"/><int name="4" value="956030004"/><int name="5" value="956030005"/><int name="6" value="956030006"/><int name="7" value="956030007"/><int name="8" value="956030008"/><int name="9" value="956030009"/><int name="10" value="956030100"/><int name="11" value="956030101"/><int name="12" value="956030102"/><int name="13" value="956030103"/><int name="14" value="956030104"/><int name="15" value="956030105"/><int name="16" value="956030106"/><int name="17" value="956030107"/><int name="18" value="956030108"/><int name="19" value="956030109"/><int name="20" value="956030200"/><int name="21" value="956030201"/><int name="22" value="956030202"/><int name="23" value="956030203"/><int name="24" value="956030204"/><int name="25" value="956030205"/><int name="26" value="956030206"/><int name="27" value="956030207"/><int name="28" value="956030208"/><int name="29" value="956030209"/><int name="30" value="956030300"/><int name="31" value="956030301"/><int name="32" value="956030302"/><int name="33" value="956030303"/><int name="34" value="956030304"/><int name="35" value="956030305"/><int name="36" value="956030306"/><int name="37" value="956030307"/><int name="38" value="956030308"/><int name="39" value="956030309"/><int name="40" value="956030400"/><int name="41" value="956030401"/><int name="42" value="956030402"/><int name="43" value="956030403"/><int name="44" value="956030404"/><int name="45" value="956030405"/><int name="46" value="956030406"/><int name="47" value="956030407"/><int name="48" value="956030408"/><int name="49" value="956030409"/></imgdir><imgdir name="deleteItem"><int name="0" value="4033204"/></imgdir></imgdir><imgdir name="Check"><imgdir name="0"><int name="npc" value="9074300"/><int name="lvmin" value="50"/><imgdir name="quest"><imgdir name="0"><int name="id" value="1731"/><int name="state" value="2"/></imgdir></imgdir></imgdir><imgdir name="1"><int name="npc" value="9074300"/><string name="endscript" value="q1732e"/><imgdir name="item"><imgdir name="0"><int name="id" value="4033204"/><int name="count" value="10"/></imgdir></imgdir></imgdir></imgdir><imgdir name="Act"><imgdir name="0"></imgdir><imgdir name="1"></imgdir></imgdir><imgdir name="Say"><imgdir name="0"><string name="0" value="나 슈피겔만, 공부하는 사나이. 마뇽의 알을 잘 부화시키기 위해 책을 좀 읽었지. 부화를 위해서는 온도 유지가 필수라고 하더군. 자네가 날 좀 도와줘야겠어."/><imgdir name="stop"></imgdir><imgdir name="yes"><string name="0" value="하늘 둥지로 가서 하프들을 처치하고 따뜻한 깃털을 구해오게. 따뜻한 깃털로 잘 감싸준다면, 온도 유지는 문제 없지 않겠나? 크크크."/></imgdir><imgdir name="no"><string name="0" value="싫은가? 왜~? 내 부탁을 들어주면 좋은 일이 생길텐데?"/></imgdir></imgdir><imgdir name="1"><imgdir name="stop"><imgdir name="item"><string name="0" value="따뜻한 깃털은 아직인가? 서둘러. 이러다 알이 잘못되기라도 하면 자네가 책임질텐가?"/></imgdir></imgdir></imgdir></imgdir></imgdir>