<?xml version="1.0" encoding="UTF-8" standalone="yes"?><imgdir name="23205.img"><imgdir name="QuestInfo"><string name="name" value="경비병을 없애라!"/><int name="area" value="10"/><int name="disableAtStartTab" value="1"/><int name="disableAtPerformTab" value="1"/><int name="disableAtCompleteTab" value="1"/><int name="autoStart" value="1"/><int name="autoAccept" value="1"/><string name="showLayerTag" value="23205"/><int name="blocked" value="1"/><int name="resignBlocked" value="1"/></imgdir><imgdir name="Check"><imgdir name="0"><int name="npc" value="2159338"/><int name="normalAutoStart" value="1"/><imgdir name="job"><int name="0" value="3100"/><int name="1" value="3110"/><int name="2" value="3111"/><int name="3" value="3112"/><int name="4" value="3001"/></imgdir></imgdir><imgdir name="1"><string name="endscript" value="q23205e"/><int name="npc" value="2159309"/><imgdir name="mob"><imgdir name="0"><int name="id" value="9300455"/><int name="count" value="3"/></imgdir></imgdir></imgdir></imgdir><imgdir name="Act"><imgdir name="0"></imgdir><imgdir name="1"></imgdir></imgdir><imgdir name="Say"><imgdir name="0"></imgdir><imgdir name="1"><imgdir name="stop"><imgdir name="mob"><string name="0" value="경비병들에게도 쩔쩔매는 거냐? 한심한 녀석!! 여신도 꼼짝 못하게 한 실력은 어디로 간 거냐!!!"/></imgdir></imgdir></imgdir></imgdir></imgdir>