<?xml version="1.0" encoding="UTF-8" standalone="yes"?><imgdir name="2385.img"><imgdir name="QuestInfo"><string name="name" value="몸보신엔 옥토퍼스"/><int name="area" value="10"/><string name="type" value="[필수]"/><string name="0" value="아직도 설희 아가씨에게 문제가 있는듯 하다. #b홍아#k를 찾아가보자."/><string name="1" value="설희 아가씨의 쇠한 기력을 되살리기 위한 특별보약을 달일 재료를 모아가자. #b커닝시티의 오른쪽 끝 포탈 이용해 공사장#k으로 나가 옥토퍼스의 다리를 모아가자."/><string name="demandSummary" value="#i4000006:# #t4000006:# #c4000006# / 10
"/><string name="rewardSummary" value="경험치 330
&apos;보약 달이기&apos; 퀘스트로 진행 가능
"/><string name="2" value="어서 설희아가씨가 나아야 할텐데...혹 더 도울일이 없는지 홍아를 찾아가 볼까?"/><int name="blocked" value="1"/></imgdir><imgdir name="Check"><imgdir name="0"><int name="npc" value="1057001"/><int name="subJobFlags" value="2"/><int name="lvmin" value="16"/><imgdir name="quest"><imgdir name="0"><int name="id" value="2384"/><int name="state" value="2"/></imgdir></imgdir></imgdir><imgdir name="1"><int name="npc" value="1057001"/><imgdir name="item"><imgdir name="0"><int name="id" value="4000006"/><int name="count" value="10"/></imgdir></imgdir></imgdir></imgdir><imgdir name="Act"><imgdir name="0"></imgdir><imgdir name="1"><int name="exp" value="330"/><imgdir name="item"><imgdir name="0"><int name="id" value="4000006"/><int name="count" value="-10"/><string name="potentialGrade" value="노멀"/></imgdir></imgdir></imgdir></imgdir><imgdir name="Say"><imgdir name="0"><string name="0" value="#h0#! 벌써 소문을 들은거야? 그래, 스티치들을 없앴는데도 설희 아가씨가 계속 잠을 못이루고 계셔. 아무래도 기력이 너무 쇠해서 그런거 같은데, 아가씨를 위한 보약을 준비해 주는 게 어떻겠어?"/><imgdir name="stop"></imgdir><imgdir name="yes"><string name="0" value="예로부터 커닝시티 마을 주민들 사이에서 약효가 뛰어나기로 소문난 것이 있지. 그건 바로 옥토퍼스 다리를 달인물이지. 신선한 옥토퍼스 다리를 사흘밤낮 달인 물은 죽은 사람도 벌떡 일어나게 한다는 전설이 있지."/><string name="1" value="아가씨께 약을 달여 드릴 수 있도록 #b옥토퍼스의 다리 10개#k를 모아와줘. 저 오른쪽... 공사장에 가면 옥토퍼스들을 볼 수 있을거야."/></imgdir><imgdir name="no"><string name="0" value="아가씨가 편찮으시면 모든게 소용없게 된다고."/></imgdir></imgdir><imgdir name="1"><string name="0" value="벌써 옥토퍼스의 다리를 모아온 거야? 신선한 재료로 정성들여 만드는 게 매우 중요해. 어서 내게 주도록 해."/><imgdir name="yes"><string name="0" value="오. 이렇게 신선한 옥토퍼스 다리는 처음 보는군. 이제 사흘 밤낮 정성들여 약을 달이는 일만 남았군."/></imgdir><imgdir name="stop"><imgdir name="item"><string name="0" value="저기 오른쪽으로 가면 공사장에 #r옥토퍼스#k들이 많이 있을거야. #b옥토퍼스의 다리 10개#k를 모아오도록 해."/></imgdir></imgdir></imgdir></imgdir></imgdir>