<?xml version="1.0" encoding="UTF-8" standalone="yes"?><imgdir name="23987.img"><imgdir name="QuestInfo"><string name="name" value="의회장의 명령3"/><int name="area" value="24"/><string name="0" value="#b에델슈티인#k의 의회장 #b안소니#k가 뭔가 할 말이 있는 모양이다."/><string name="1" value="안소니는 아직도 에델슈타인의 예산이 부족하다며 이번에는 민첩성의 크리스탈을 구해 달라고 한다. 대체 이걸 어디에 쓰겠다고 구해 달라는 거야...

#i4005002##t4005002#  #b#c4005002# / 1#k"/><string name="2" value="안소니에게 민첩성의 크리스탈을 전했다."/></imgdir><imgdir name="Check"><imgdir name="0"><int name="npc" value="2152007"/><int name="lvmin" value="55"/><imgdir name="quest"><imgdir name="0"><int name="id" value="23986"/><int name="state" value="2"/></imgdir></imgdir></imgdir><imgdir name="1"><int name="npc" value="2152007"/><imgdir name="item"><imgdir name="0"><int name="id" value="4005002"/><int name="count" value="1"/></imgdir></imgdir></imgdir></imgdir><imgdir name="Act"><imgdir name="0"></imgdir><imgdir name="1"><int name="exp" value="15600"/><imgdir name="item"><imgdir name="0"><int name="id" value="4005002"/><int name="count" value="-1"/></imgdir></imgdir></imgdir></imgdir><imgdir name="Say"><imgdir name="0"><string name="0" value="오, 자네로군. 마침 잘 만났네. 부탁할 것이 하나 있는데... 아니 왜 표정을 찌푸리는 건가! 이게 다 공익을 위한 건데 좋게 협조 좀 해주게나."/><imgdir name="stop"></imgdir><imgdir name="yes"><string name="0" value="이번에 구해야 할 건 #b민첩성의 크리스탈#k이라네. 뭐... 구하기 쉽지 않은 물건이긴 하지. 하지만 그게 있다면 내 안전에 도움이...가 아니라! 에델슈타인에 크게 도움이 될 거라네!"/></imgdir><imgdir name="no"><string name="0" value="몇 번 일을 도와줘서 좋게 봤는데 영 그렇지도 않은 모양이군. "/></imgdir></imgdir><imgdir name="1"><string name="0" value="민첩성의 크리스탈을 가져 왔군! 이것만 있다면 위기 상황에서도 재빠르게 탈출...이 아니라, 사람들을 구출할 수 있지 않을까 했다네! 하! 하하..."/><imgdir name="yes"><string name="0" value="도와줘서 고맙네. 자네야말로 에델슈타인 시민들이 배워야 할 도시를 사랑하는 마음을 가졌군."/></imgdir><imgdir name="stop"><imgdir name="item"><string name="0" value="아직 #b민첩성의 크리스탈#k을 구하지 못한 건가? 흠... 뭐, 구하기 쉽지는 않다고 하지. 알아서 잘 구해 보게나."/></imgdir></imgdir></imgdir></imgdir></imgdir>