<?xml version="1.0" encoding="UTF-8" standalone="yes"?><imgdir name="31108.img"><imgdir name="QuestInfo"><string name="name" value="마을의 수호자1"/><int name="area" value="47"/><string name="0" value="빅 헤드워드가 자신을 도와줄 사람을 찾고 있다고 한다. 빅 헤드워드에게 가보자."/><string name="1" value="빅 헤드워드를 도와 마을 주변에서 주민들을 위협하는 몬스터들을 처치해야 한다.

"/><string name="2" value="빅 헤드워드를 도와 마을 주위의 #o8600001#들을 처치하고 마을을 지키는 것을 도왔다."/><string name="demandSummary" value="\n\n#o8600001# #r#a311081##k"/></imgdir><imgdir name="Check"><imgdir name="0"><int name="npc" value="2142003"/><int name="lvmin" value="160"/><imgdir name="quest"><imgdir name="0"><int name="id" value="31104"/><int name="state" value="2"/></imgdir></imgdir></imgdir><imgdir name="1"><int name="npc" value="2142003"/><imgdir name="mob"><imgdir name="0"><int name="id" value="8600001"/><int name="count" value="500"/></imgdir></imgdir></imgdir></imgdir><imgdir name="Act"><imgdir name="0"></imgdir><imgdir name="1"><int name="exp" value="3416500"/></imgdir></imgdir><imgdir name="Say"><imgdir name="0"><string name="0" value="안녕하세요. 지난 번엔 죄송했어요. 마을이 이렇게 된 후로 낯선 사람들을 경계하는 것은 어쩔 수 없는 일이라서요. 그나저나 저를 좀 도와주시겠어요?"/><imgdir name="stop"></imgdir><imgdir name="yes"><string name="0" value="그들의 공격 이후로 전 미용사이길 포기하고 마을의 수호자가되기로 결심했답니다. 저의 엘레강스한 취향에 전혀 맞지 않는 이런 갑옷을 입고요. 
앗 이게 아니라 저를 대신해 마을 주민들을 위협하는 몬스터를 처치해주세요. 제가 해야 할 일들이 너무 많아서요. 심지어 머리 손질을 못한지 이틀이 넘었다구요! 그럼 잘 부탁드려요. 일단 #b#o8600001# 500마리#k 정도 처치해주세요."/></imgdir><imgdir name="no"><string name="0" value="설마 지난 번 일로 마음 상하신 건 아니시죠?"/></imgdir></imgdir><imgdir name="1"><string name="0" value="부탁한 일은 다 처리하신건가요?"/><imgdir name="yes"><string name="0" value="감사합니다. 다음에도 잘 부탁드려요."/></imgdir><imgdir name="stop"><imgdir name="mob"><string name="0" value="아직 다 처치하지 못하셨나요? 마을의 안전을 위해 좀 더 분발해주세요."/></imgdir></imgdir></imgdir></imgdir></imgdir>