<?xml version="1.0" encoding="UTF-8" standalone="yes"?><imgdir name="3344.img"><imgdir name="QuestInfo"><string name="name" value="마가티아의 비밀"/><string name="parent" value="드랭의 노트"/><int name="order" value="6"/><string name="1" value="#t4031737#로 읽을 수 있게 된 #t4161032#... 그 숨겨진 장의 이야기. 그것은 바로 #b#m261000000#라는 마을이 탄생하게 된 배경에 관한 이야기#k였다. #p2020005#는 모든 진실을 알게 된 후 다시 그를 찾아오라고 하는데... "/><string name="2" value="#m261000000#... 연금술의 마을에 감춰진 비밀. 그 모든 것을 알고 있는 자. 알케스터를 찾아가 보자."/><int name="area" value="43"/></imgdir><imgdir name="Check"><imgdir name="1"><int name="npc" value="2020005"/><imgdir name="item"><imgdir name="0"><int name="id" value="4161033"/><int name="count" value="1"/></imgdir></imgdir></imgdir><imgdir name="0"><int name="npc" value="2020005"/><imgdir name="quest"><imgdir name="0"><int name="id" value="3343"/><int name="state" value="2"/></imgdir></imgdir><int name="lvmin" value="85"/></imgdir></imgdir><imgdir name="Say"><imgdir name="1"><string name="0" value="...왔군. 노트는 모두 읽은 건가? "/></imgdir><imgdir name="0"><string name="0" value="자, 이제 노트를 읽을 수 있게 되었다네... 어디 무슨 내용이 적혀 있는지 한 번 볼까...? ...잠깐... 이 노트는... #m261000000#에 관한... 자네는 이 노트의 주인이 누구인지 아는 건가?"/><string name="1" value="아는 모양이군... 그런 것이었군. #m261000000#... 이 노트에 쓰여있는 건 #b#m261000000#의 탄생에 얽힌 이야기#k라네... 아직까지 아무에게도 밝혀지지 않은 진실... 자네가 어떻게 이 노트를 구했는지 모르겠군."/><string name="2" value="하지만 영원히 감출 수 있는 비밀은 없는 법. 자네가 노트를 가지고 있다는 건, 그 비밀을 알만한 사람이기 때문이겠지. 협회장들은 마음에 들어하지 않겠지만... 자, 자네가 가져온 노트를 받게."/><imgdir name="yes"><string name="0" value="모든 진실을 알게 되거든 다시 이곳을 찾아와 주게."/></imgdir><imgdir name="no"><string name="0" value="진실이 두렵다면 그것도 상관 없겠지."/></imgdir></imgdir></imgdir><imgdir name="Act"><imgdir name="0"><imgdir name="item"><imgdir name="0"><int name="id" value="4161033"/><int name="count" value="1"/><int name="gender" value="2"/></imgdir></imgdir></imgdir><imgdir name="1"><imgdir name="item"><imgdir name="0"><int name="id" value="4161033"/><int name="count" value="-1"/></imgdir></imgdir><int name="exp" value="37420"/></imgdir></imgdir></imgdir>