<?xml version="1.0" encoding="UTF-8" standalone="yes"?><imgdir name="6502.img"><imgdir name="QuestInfo"><string name="name" value="의심하는 표정 짓기"/><int name="area" value="10"/><string name="0" value="대박 기획 대표 #b#p1052121##k에게 휘말려 #b연기 수업#k을 받기로 했다. 어떤 수업일까? #b커닝스퀘어#k의 #p1052121#에게 말을 걸어보자."/><string name="1" value="#p1052121#는 연기는 다른 사람을 관찰하고 그대로 따라하는 것이 최고라 했다. 그러면서 #b#m100000000##k로 가서 #b#p1012003##k을 잘 관찰하면 표정 하나를 얻을 수 있을 거라는데... "/><string name="2" value="#p1012003#을 보고 의심하는 표정 짓는 법을 배웠다."/></imgdir><imgdir name="Check"><imgdir name="0"><int name="npc" value="1052121"/><int name="charmMin" value="30"/><imgdir name="quest"><imgdir name="0"><int name="id" value="6501"/><int name="state" value="2"/></imgdir></imgdir></imgdir><imgdir name="1"><int name="npc" value="1012003"/><string name="endscript" value="q6502e"/></imgdir></imgdir><imgdir name="Act"><imgdir name="0"></imgdir><imgdir name="1"></imgdir></imgdir><imgdir name="Say"><imgdir name="0"><string name="0" value="연기를 잘 하는 법은 간단해요. 다양한 표정을 지을 줄 알면 돼요. 하지만 사람마다 성격이 모두 달라 모든 표정을 짓기는 쉽지 않죠. "/><string name="1" value="그럴 때 쓰는 방법은 간단해요. 다른 성격을 가진 사람을 잘 관찰해서 그 표정을 그대로 따라하면 그와 같은 표정을 연기할 수 있게 되죠. 이해 하셨나요? "/><imgdir name="stop"></imgdir><imgdir name="yes"><string name="0" value="그럼 첫 번째 연기 수업입니다. #b#m100000000##k로 가서 #b#p1012003##k을 잘 관찰하고 그의 표정을 따라해 보세요. 표정 하나를 얻을 수 있을 거예요."/></imgdir><imgdir name="no"><string name="0" value="연예인이 될 생각 없다고 이 수업까지 소홀히 하지는 않길 바래요."/></imgdir></imgdir><imgdir name="1"><imgdir name="stop"><imgdir name="npc"><string name="0" value="아직 #b#p1012003##k에게는 안 간 건가요? 그는 #b#m100000000##k에 있어요. "/></imgdir></imgdir></imgdir></imgdir></imgdir>